[
  {
    "id": 1,
    "priority": 100,
    "action": {
      "type": "redirect",
      "redirect": {
        "transform": {
          "scheme": "https",
          "host": "ajax.loli.net"
        }
      }
    },
    "condition": {
      "urlFilter": "ajax.googleapis.com",
      "requestDomains": ["ajax.googleapis.com"],
      "resourceTypes": [
        "main_frame",
        "sub_frame",
        "stylesheet",
        "script",
        "image",
        "font",
        "object",
        "xmlhttprequest",
        "ping",
        "csp_report",
        "media",
        "websocket",
        "webtransport",
        "webbundle",
        "other"
      ]
    }
  },
  {
    "id": 2,
    "priority": 100,
    "action": {
      "type": "redirect",
      "redirect": {
        "transform": {
          "scheme": "https",
          "host": "cdnjs.loli.net"
        }
      }
    },
    "condition": {
      "urlFilter": "cdnjs.cloudflare.com/ajax/libs",
      "requestDomains": ["cdnjs.cloudflare.com"],
      "resourceTypes": [
        "main_frame",
        "sub_frame",
        "stylesheet",
        "script",
        "image",
        "font",
        "object",
        "xmlhttprequest",
        "ping",
        "csp_report",
        "media",
        "websocket",
        "webtransport",
        "webbundle",
        "other"
      ]
    }
  },
  {
    "id": 3,
    "priority": 100,
    "action": {
      "type": "redirect",
      "redirect": {
        "transform": {
          "scheme": "https",
          "host": "fonts.loli.net"
        }
      }
    },
    "condition": {
      "urlFilter": "fonts.googleapis.com",
      "requestDomains": ["fonts.googleapis.com"],
      "resourceTypes": [
        "main_frame",
        "sub_frame",
        "stylesheet",
        "script",
        "image",
        "font",
        "object",
        "xmlhttprequest",
        "ping",
        "csp_report",
        "media",
        "websocket",
        "webtransport",
        "webbundle",
        "other"
      ]
    }
  },
  {
    "id": 4,
    "priority": 100,
    "action": {
      "type": "redirect",
      "redirect": {
        "transform": {
          "scheme": "https",
          "host": "gstatic.loli.net"
        }
      }
    },
    "condition": {
      "urlFilter": "fonts.gstatic.com",
      "requestDomains": ["fonts.gstatic.com"],
      "resourceTypes": [
        "main_frame",
        "sub_frame",
        "stylesheet",
        "script",
        "image",
        "font",
        "object",
        "xmlhttprequest",
        "ping",
        "csp_report",
        "media",
        "websocket",
        "webtransport",
        "webbundle",
        "other"
      ]
    }
  },
  {
    "id": 5,
    "priority": 100,
    "action": {
      "type": "redirect",
      "redirect": {
        "transform": {
          "scheme": "https",
          "host": "gravatar.loli.net"
        }
      }
    },
    "condition": {
      "urlFilter": "gravatar.com",
      "requestDomains": [
        "secure.gravatar.com",
        "www.gravatar.com",
        "cn.gravatar.com",
        "en.gravatar.com"
      ],
      "resourceTypes": [
        "main_frame",
        "sub_frame",
        "stylesheet",
        "script",
        "image",
        "font",
        "object",
        "xmlhttprequest",
        "ping",
        "csp_report",
        "media",
        "websocket",
        "webtransport",
        "webbundle",
        "other"
      ]
    }
  },
  {
    "id": 6,
    "priority": 100,
    "action": {
      "type": "redirect",
      "redirect": {
        "transform": {
          "scheme": "https",
          "host": "themes.loli.net"
        }
      }
    },
    "condition": {
      "urlFilter": "themes.googleusercontent.com",
      "requestDomains": ["themes.googleusercontent.com"],
      "resourceTypes": [
        "main_frame",
        "sub_frame",
        "stylesheet",
        "script",
        "image",
        "font",
        "object",
        "xmlhttprequest",
        "ping",
        "csp_report",
        "media",
        "websocket",
        "webtransport",
        "webbundle",
        "other"
      ]
    }
  }
]
